multicloud_diagrams/__init__.py
multicloud_diagrams/providers/aws.json
multicloud_diagrams/providers/aws2024.json
multicloud_diagrams/providers/azure.json
multicloud_diagrams/providers/core.json
multicloud_diagrams/providers/fallback.json
multicloud_diagrams/providers/gcp.json
multicloud_diagrams/providers/onprem.json
multicloud_diagrams-0.3.116.dist-info/LICENSE
multicloud_diagrams-0.3.116.dist-info/METADATA
multicloud_diagrams-0.3.116.dist-info/WHEEL
multicloud_diagrams-0.3.116.dist-info/RECORD
