Metadata-Version: 2.1
Name: multicloud-diagrams
Version: 0.3.116
Summary: Library to generate DRAW.IO compatible diagrams to represent Cloud infrastructure. AWS Cloud supported.
License: MIT
Author: Roman Tsypuk
Author-email: tsypuk.conf@gmail.com
Requires-Python: >=3.7,<4.0
Classifier: License :: OSI Approved :: MIT License
Classifier: Programming Language :: Python :: 3
Classifier: Programming Language :: Python :: 3.7
Classifier: Programming Language :: Python :: 3.8
Classifier: Programming Language :: Python :: 3.9
Classifier: Programming Language :: Python :: 3.10
Classifier: Programming Language :: Python :: 3.11
Classifier: Programming Language :: Python :: 3.12
Requires-Dist: pyyaml (>=6.0,<7.0)
Requires-Dist: requests (>=2.31.0,<3.0.0)
